motrixsim-0.5.0.dist-info/METADATA
motrixsim-0.5.0.dist-info/WHEEL
motrixsim-0.5.0.dist-info/licenses/LICENSE
motrixsim-0.5.0.dist-info/licenses/NOTICE
motrixsim/ik.py
motrixsim/ik.pyi
motrixsim/interactive_viewer.py
motrixsim/low.py
motrixsim/low.pyi
motrixsim/msd.pyi
motrixsim/render/widgets.py
motrixsim/render/widgets.pyi
motrixsim/render/__init__.pyi
motrixsim/run.py
motrixsim/viewer.pyi
motrixsim/__init__.py
motrixsim/__init__.pyi
motrixsim/motrixsim.cp310-win_amd64.pyd
motrixsim-0.5.0.dist-info/RECORD
