Metadata-Version: 2.4
Name: motrixsim
Version: 0.5.0
Classifier: Programming Language :: Rust
Classifier: Programming Language :: Python :: Implementation :: CPython
Classifier: Programming Language :: Python :: Implementation :: PyPy
Classifier: Programming Language :: Python :: 3.10
Classifier: Programming Language :: Python :: 3.11
Classifier: Programming Language :: Python :: 3.12
Classifier: Programming Language :: Python :: 3.13
Classifier: Operating System :: Microsoft :: Windows
Classifier: Operating System :: POSIX :: Linux
Classifier: License :: OSI Approved :: Apache Software License
Requires-Dist: absl-py==2.1.0
Requires-Dist: numpy
Requires-Dist: pytest ; extra == 'test'
Requires-Dist: pytest-cov ; extra == 'test'
Requires-Dist: scipy ; extra == 'test'
Requires-Dist: ruff ; extra == 'lint'
Requires-Dist: onnxruntime>=1.22.0 ; extra == 'demo'
Requires-Dist: numpy-quaternion>=2024.0.8 ; extra == 'demo'
Requires-Dist: imageio[ffmpeg]>=2.37.2 ; extra == 'demo'
Requires-Dist: mujoco>=3.3.3 ; extra == 'mujoco-demo'
Requires-Dist: sphinx ; extra == 'docs'
Requires-Dist: autodocsumm ; extra == 'docs'
Requires-Dist: pydata-sphinx-theme ; extra == 'docs'
Requires-Dist: myst-parser ; extra == 'docs'
Requires-Dist: sphinx-copybutton ; extra == 'docs'
Requires-Dist: sphinx-subfigure ; extra == 'docs'
Requires-Dist: sphinxcontrib-video ; extra == 'docs'
Requires-Dist: sphinx-togglebutton ; extra == 'docs'
Requires-Dist: sphinx-design ; extra == 'docs'
Provides-Extra: test
Provides-Extra: lint
Provides-Extra: demo
Provides-Extra: mujoco_demo
Provides-Extra: docs
License-File: LICENSE
License-File: NOTICE
Summary: A high-performance physics simulation engine designed for multibody dynamics and robotics simulation.
Keywords: 
Author-email: Motphys <developers@motphys.com>
License: Apache-2.0
Requires-Python: >=3.10, <3.14
Project-URL: repository, https://github.com/Motphys/motrixsim-docs
Project-URL: documentation, https://motrixsim.readthedocs.io
